{
  "train_rows": 7903,
  "test_rows": 1976,
  "n_features": 39,
  "class_balance_train": {
    "0": 0.5009,
    "1": 0.4991
  },
  "missing_rates": {
    "gameId": 0.0,
    "blueWins": 0.0,
    "blueWardsPlaced": 0.0,
    "blueWardsDestroyed": 0.0,
    "blueFirstBlood": 0.0,
    "blueKills": 0.0,
    "blueDeaths": 0.0,
    "blueAssists": 0.0,
    "blueEliteMonsters": 0.0,
    "blueDragons": 0.0,
    "blueHeralds": 0.0,
    "blueTowersDestroyed": 0.0,
    "blueTotalGold": 0.0,
    "blueAvgLevel": 0.0,
    "blueTotalExperience": 0.0,
    "blueTotalMinionsKilled": 0.0,
    "blueTotalJungleMinionsKilled": 0.0,
    "blueGoldDiff": 0.0,
    "blueExperienceDiff": 0.0,
    "blueCSPerMin": 0.0,
    "blueGoldPerMin": 0.0,
    "redWardsPlaced": 0.0,
    "redWardsDestroyed": 0.0,
    "redFirstBlood": 0.0,
    "redKills": 0.0,
    "redDeaths": 0.0,
    "redAssists": 0.0,
    "redEliteMonsters": 0.0,
    "redDragons": 0.0,
    "redHeralds": 0.0,
    "redTowersDestroyed": 0.0,
    "redTotalGold": 0.0,
    "redAvgLevel": 0.0,
    "redTotalExperience": 0.0,
    "redTotalMinionsKilled": 0.0,
    "redTotalJungleMinionsKilled": 0.0,
    "redGoldDiff": 0.0,
    "redExperienceDiff": 0.0,
    "redCSPerMin": 0.0,
    "redGoldPerMin": 0.0
  },
  "top_correlated_features": {
    "redGoldDiff": -0.5124,
    "blueGoldDiff": 0.5124,
    "redExperienceDiff": -0.4895,
    "blueExperienceDiff": 0.4895,
    "blueTotalGold": 0.4167,
    "blueGoldPerMin": 0.4167,
    "redGoldPerMin": -0.4107,
    "redTotalGold": -0.4107,
    "redTotalExperience": -0.3918,
    "blueTotalExperience": 0.391
  }
}